Metadata-Version: 1.1
Name: krosstrading
Version: 0.1
Summary: Helloworld project for CI and Coverage
Home-page: https://github.com/nnnlife/krosstrading
Author: Yongwoo Park
Author-email: nnnlife@gmail.com
License: MIT
Platform: UNKNOWN
Classifier: Development Status :: 1 - Planning
Classifier: Environment :: Web Environment
Classifier: Intended Audience :: Developers
Classifier: License :: OSI Approved :: Apache Software License
Classifier: Operating System :: OS Independent
Classifier: Programming Language :: Python :: 3.8
